mkdocs_ai_summary/__init__.py
mkdocs_ai_summary/cache.py
mkdocs_ai_summary/chatgpt_api.py
mkdocs_ai_summary/plugin.py
mkdocs_ai_summary/tongyi_api.py
mkdocs_ai_summary-0.2.6.dist-info/LICENSE
mkdocs_ai_summary-0.2.6.dist-info/METADATA
mkdocs_ai_summary-0.2.6.dist-info/WHEEL
mkdocs_ai_summary-0.2.6.dist-info/entry_points.txt
mkdocs_ai_summary-0.2.6.dist-info/top_level.txt
mkdocs_ai_summary-0.2.6.dist-info/RECORD
