Metadata-Version: 2.1
Name: mkdocs-ai-summary
Version: 0.2.6
Summary: A mkdocs plugin to generage summary with the help of AI.
Author-email: Yang Zhang <mail@yangzhang.site>
License: MIT License
Project-URL: Homepage, https://github.com/AIboy996/mkdocs-ai-summary
Keywords: mkdocs,AI,blog,chatgpt
Classifier: Development Status :: 3 - Alpha
Classifier: Intended Audience :: Developers
Classifier: Programming Language :: Python :: 3.10
Classifier: Programming Language :: Python :: 3.11
Classifier: Programming Language :: Python :: 3.12
Classifier: License :: OSI Approved :: MIT License
Classifier: Operating System :: OS Independent
Requires-Python: >=3.10
License-File: LICENSE
Requires-Dist: mkdocs>=1.5.3
Provides-Extra: tongyi
Requires-Dist: dashscope; extra == "tongyi"
Provides-Extra: chatgpt
Requires-Dist: openai; extra == "chatgpt"
